anymodel/__init__.py
anymodel/__main__.py
anymodel/mapper.py
anymodel/storages/__init__.py
anymodel/storages/base.py
anymodel/storages/filesystem.py
anymodel/storages/memory.py
anymodel/storages/short_long.py
anymodel/storages/sqlalchemy.py
anymodel/types/__init__.py
anymodel/types/collections.py
anymodel/types/entity.py
anymodel/types/mappings.py
anymodel/types/relations.py
anymodel/types/utils.py
anymodel/utilities/__init__.py
anymodel/utilities/identity_map.py
anymodel/utilities/migrations.py
anymodel-0.1.0.dist-info/licenses/LICENSE
anymodel-0.1.0.dist-info/METADATA
anymodel-0.1.0.dist-info/WHEEL
anymodel-0.1.0.dist-info/top_level.txt
anymodel-0.1.0.dist-info/RECORD
