Metadata-Version: 2.4
Name: anymodel
Version: 0.1.0
Summary: A modern data mapper library built on Pydantic
Requires-Python: >=3.12
License-File: LICENSE
Requires-Dist: alembic>=1.14.0
Requires-Dist: psycopg2-binary>=2.9.10
Requires-Dist: pydantic>=2.9.2
Requires-Dist: pyheck>=0.1.5
Requires-Dist: sqlalchemy>=2.0.36
Requires-Dist: sqlmodel>=0.0.22
Dynamic: license-file
